regressionmetrics/__init__.py
regressionmetrics/keras.py
regressionmetrics/metrics.py
regressionmetrics-1.4.0.dist-info/LICENSE
regressionmetrics-1.4.0.dist-info/METADATA
regressionmetrics-1.4.0.dist-info/WHEEL
regressionmetrics-1.4.0.dist-info/top_level.txt
regressionmetrics-1.4.0.dist-info/zip-safe
regressionmetrics-1.4.0.dist-info/RECORD
