Metadata-Version: 2.1
Name: regressionmetrics
Version: 1.4.0
Summary: Regression Metrics Calculation Made easy.
Home-page: http://github.com/ashishpatel26/regressionmetrics
Author: ashishpatel26
Author-email: ashishpatel.ce.2011@gmail.com
License: UNKNOWN
Keywords: regressionmertics,regression,metrics,regression metrics,regression metrics calculation,regression metrics calculation made easy
Platform: any
Classifier: License :: OSI Approved :: MIT License
Classifier: Programming Language :: Python :: 3
Requires-Dist: pandas
Requires-Dist: numpy
Requires-Dist: scikit-learn
Requires-Dist: tensorflow-cpu
Requires-Dist: tensorflow-gpu
